mkdocs_custom_fences/__init__.py
mkdocs_custom_fences/md_render.py
mkdocs_custom_fences-0.1.2.dist-info/METADATA
mkdocs_custom_fences-0.1.2.dist-info/WHEEL
mkdocs_custom_fences-0.1.2.dist-info/top_level.txt
mkdocs_custom_fences-0.1.2.dist-info/RECORD
