Metadata-Version: 2.1
Name: mkdocs-custom-fences
Version: 0.1.2
Summary: A series of snippets to create custom fences for mkdocs 
Home-page: https://github.com/Mara-Li/mkdocs_custom_fences
Author: Mara-Li
Author-email: mara-li@icloud.com
License: AGPL
Keywords: mkdocs,custom_fences,pymdownx,markdown extension,markdown,md
Classifier: Natural Language :: English
Classifier: Natural Language :: French
Classifier: Topic :: Text Processing :: Markup :: Markdown
Classifier: License :: OSI Approved :: GNU Affero General Public License v3 or later (AGPLv3+)
Classifier: Programming Language :: Python :: 3
Classifier: Programming Language :: Python :: 3.6
Classifier: Programming Language :: Python :: 3.7
Classifier: Programming Language :: Python :: 3.8
Classifier: Programming Language :: Python :: 3.9
Requires-Python: >=3.7
Requires-Dist: Markdown
Requires-Dist: pyYaml
Requires-Dist: mdx-wikilink-plus
Requires-Dist: pymdown-extensions
